seqspec_parse/__init__.py
seqspec_parse/process.py
seqspec_parse-0.1.1.dist-info/METADATA
seqspec_parse-0.1.1.dist-info/WHEEL
seqspec_parse-0.1.1.dist-info/RECORD
