Metadata-Version: 2.1
Name: seqspec-parse
Version: 0.1.1
Summary: Parse a seqspec file for use with UMI-tools
Author: Eric Che
Author-email: eric.che@childrens.harvard.edu
Requires-Python: >=3.9,<4.0
Classifier: Programming Language :: Python :: 3
Classifier: Programming Language :: Python :: 3.9
Classifier: Programming Language :: Python :: 3.10
Classifier: Programming Language :: Python :: 3.11
Requires-Dist: seqspec (>=0.1.1,<0.2.0)
Requires-Dist: typeguard (>=4.1.5,<5.0.0)
